zipcode/__init__.py
zipcode-4.0.0.data/scripts/build_zipcode_database
zipcode-4.0.0.dist-info/METADATA
zipcode-4.0.0.dist-info/RECORD
zipcode-4.0.0.dist-info/WHEEL
zipcode-4.0.0.dist-info/top_level.txt
