Metadata-Version: 2.1
Name: zipcode
Version: 4.0.0
Summary: A simple python package for dealing with  zip codes in python.  Free for non commerial use, for commercial use, you need a license. Check out the README on GitHub for details.
Home-page: https://github.com/buckmaxwell/zipcode
Author: Max Buck
Author-email: maxbuckdeveloper@gmail.com
License: MIT
Keywords: zip code zipcode
Platform: UNKNOWN
Classifier: Development Status :: 5 - Production/Stable
Classifier: Intended Audience :: Developers
Classifier: Topic :: Software Development :: Build Tools
Classifier: License :: OSI Approved :: MIT License
Classifier: Programming Language :: Python :: 2
Classifier: Programming Language :: Python :: 2.6
Classifier: Programming Language :: Python :: 2.7
Classifier: Programming Language :: Python :: 3
Classifier: Programming Language :: Python :: 3.2
Classifier: Programming Language :: Python :: 3.3
Classifier: Programming Language :: Python :: 3.4
Requires-Dist: haversine
Requires-Dist: SQLAlchemy
